[
  {
    "id": "p1",
    "name": "Selmi Galo Pena",
    "short": "Macarrão de Sêmola",
    "description": "Pasta de sêmola tipo pena, ideal para diversos molhos. Tempo de cozimento de 5 a 7 minutos.",
    "price": 1.5,
    "categoryId": "pantry",
    "image": "products_0002_Capa-1.png"
  },
  {
    "id": "p2",
    "name": "Ricolino Kranky",
    "short": "Hojuela de maíz con cobertura de chocolate",
    "description": "Crujientes hojuelas de maíz cubiertas con un delicioso sabor a chocolate. Un snack divertido y sabroso.",
    "price": 0.5,
    "categoryId": "candy",
    "image": "products_0003_20231206_132442.png"
  },
  {
    "id": "p3",
    "name": "Ricolino Bubu Lubu Mini",
    "short": "Malvavisco con relleno de fresa",
    "description": "Pequeño malvavisco con un delicioso relleno de jalea sabor a fresa y una cobertura de chocolate.",
    "price": 0.4,
    "categoryId": "candy",
    "image": "products_0004_20231206_132434.png"
  },
  {
    "id": "p4",
    "name": "Arcor Sapito Cacahuate",
    "short": "Chocolate relleno con cacahuate",
    "description": "Divertida figura con sabor a chocolate, rellena con maní y cereal crocante.",
    "price": 0.3,
    "categoryId": "candy",
    "image": "products_0005_20231206_132428.png"
  },
  {
    "id": "p5",
    "name": "Muibon Roll",
    "short": "Barquillo relleno de crema de avellana",
    "description": "Crujiente barquillo relleno de crema de avellana con una deliciosa cubierta de chocolate y cacahuates.",
    "price": 0.6,
    "categoryId": "candy",
    "image": "products_0006_20231206_132420.png"
  },
  {
    "id": "p6",
    "name": "Hershey's Cookies 'N' Creme",
    "short": "Dulce sabor a crema con galletas",
    "description": "La clásica barra de chocolate blanco Hershey's con trocitos de galleta de chocolate.",
    "price": 1.2,
    "categoryId": "candy",
    "image": "products_0007_20231206_132347.png"
  },
  {
    "id": "p7",
    "name": "MilkyWay Bar",
    "short": "Chocolate con caramelo y nougat",
    "description": "Una combinación perfecta de nougat, caramelo y chocolate con leche.",
    "price": 1.1,
    "categoryId": "candy",
    "image": "products_0008_20231206_132341.png"
  },
  {
    "id": "p8",
    "name": "Vieira Príncipe Sabor Chocolate",
    "short": "Galletas rellenas de chocolate",
    "description": "Crujientes galletas tipo sándwich con un cremoso relleno de chocolate.",
    "price": 2,
    "categoryId": "snacks",
    "image": "products_0009_20231206_132315.png"
  },
  {
    "id": "p9",
    "name": "Jell-O Gelatina Sabor Frambuesa",
    "short": "Polvo para preparar gelatina",
    "description": "Polvo para preparar una deliciosa gelatina sabor frambuesa, fortificada con vitamina C.",
    "price": 0.8,
    "categoryId": "pantry",
    "image": "products_0010_20231206_132305.png"
  },
  {
    "id": "p10",
    "name": "Jell-O Gelatina Sabor Naranja",
    "short": "Polvo para preparar gelatina",
    "description": "Polvo para preparar una refrescante gelatina sabor naranja, fortificada con vitamina C.",
    "price": 0.8,
    "categoryId": "pantry",
    "image": "products_0011_20231206_132242.png"
  },
  {
    "id": "p11",
    "name": "Jell-O Gelatina Sabor Limón",
    "short": "Polvo para preparar gelatina",
    "description": "Polvo para preparar una ácida y deliciosa gelatina sabor limón, fortificada con vitamina C.",
    "price": 0.8,
    "categoryId": "pantry",
    "image": "products_0012_20231206_132237.png"
  },
  {
    "id": "p12",
    "name": "Gourmet Barquillos Sabor Coco",
    "short": "Barquillos rellenos de crema de coco",
    "description": "Crujientes barquillos tipo wafer rellenos con una suave crema de coco.",
    "price": 1.8,
    "categoryId": "snacks",
    "image": "products_0013_20231206_132218.png"
  },
  {
    "id": "p13",
    "name": "Gourmet Barquillos Sabor a Nata",
    "short": "Barquillos rellenos de crema de nata",
    "description": "Crujientes barquillos tipo wafer rellenos con una cremosa y dulce nata.",
    "price": 1.8,
    "categoryId": "snacks",
    "image": "products_0014_20231206_132211.png"
  },
  {
    "id": "p14",
    "name": "Knorr Sopa Mickey y Amigos",
    "short": "Sopa de pasta con forma de Mickey",
    "description": "Divertida sopa de pasta con figuras de Mickey Mouse y sus amigos, ideal para niños.",
    "price": 1.2,
    "categoryId": "pantry",
    "image": "products_0015_20231206_132155.png"
  },
  {
    "id": "p15",
    "name": "Knorr Sopa Estrellas",
    "short": "Sopa de pasta sabor casero",
    "description": "Clásica sopa de estrellas con sabor casero, lista en 10 minutos.",
    "price": 1.1,
    "categoryId": "pantry",
    "image": "products_0016_20231206_132147.png"
  },
  {
    "id": "p16",
    "name": "Trident Extra Strong",
    "short": "Goma de mascar sabor a menta fuerte",
    "description": "Chicle sin azúcar con microcápsulas para un sabor fresco y duradero con extra fuerza.",
    "price": 1.5,
    "categoryId": "candy",
    "image": "products_0017_20231206_132138.png"
  },
  {
    "id": "p17",
    "name": "Trident Freshmint",
    "short": "Goma de mascar sabor a menta fresca",
    "description": "Chicle sin azúcar con microcápsulas para un sabor a menta refrescante y duradero.",
    "price": 1.5,
    "categoryId": "candy",
    "image": "products_0018_20231206_132133.png"
  },
  {
    "id": "p18",
    "name": "Nutro Chocolate Cream Wafers",
    "short": "Wafers de crema sabor a chocolate",
    "description": "Capas cremosas de diversión crujiente. Wafers con sabor a chocolate.",
    "price": 1.3,
    "categoryId": "snacks",
    "image": "products_0019_20231206_132120.png"
  },
  {
    "id": "p19",
    "name": "Pop Mania Assorted Fruits",
    "short": "Chupetes de frutas surtidas rellenos de chicle",
    "description": "Bolsa de 50 chupetes de sabores surtidos: manzana verde, mandarina y fresa, rellenos de chicle.",
    "price": 5,
    "categoryId": "candy",
    "image": "products_0020_20231206_132112.png"
  },
  {
    "id": "p20",
    "name": "Pop Mania Strawberry Tongue Painting",
    "short": "Chupetes de fresa pinta lengua",
    "description": "Bolsa de 50 chupetes de fresa que pintan la lengua, rellenos de chicle.",
    "price": 5,
    "categoryId": "candy",
    "image": "products_0021_20231206_132100.png"
  },
  {
    "id": "p21",
    "name": "Pop Mania Extra Tongue Painting",
    "short": "Chupetes de uva y fresa pinta lengua",
    "description": "Bolsa de 50 chupetes de sabores uva y fresa que pintan la lengua, rellenos de chicle.",
    "price": 5,
    "categoryId": "candy",
    "image": "products_0022_20231206_132047.png"
  },
  {
    "id": "p22",
    "name": "Sabritas Adobadas",
    "short": "Papas fritas sabor adobo",
    "description": "Crujientes papas fritas con el clásico y delicioso sabor a adobo.",
    "price": 1,
    "categoryId": "snacks",
    "image": "products_0023_20231206_132021.png"
  },
  {
    "id": "p23",
    "name": "Sabritas Original",
    "short": "Papas fritas con sal",
    "description": "Las papas fritas originales, con solo tres ingredientes: papa, aceite y sal.",
    "price": 1,
    "categoryId": "snacks",
    "image": "products_0024_20231206_132013.png"
  },
  {
    "id": "p24",
    "name": "Diamir Tomate Frito",
    "short": "Tomate frito en conserva",
    "description": "Tomate frito estilo casero, listo para usar en tus guisos y platos. Sin gluten.",
    "price": 2.5,
    "categoryId": "pantry",
    "image": "products_0025_20231206_131932.png"
  },
  {
    "id": "p25",
    "name": "Kellogg's Zucaritas",
    "short": "Hojuelas de maíz escarchadas",
    "description": "Clásicas hojuelas de maíz azucaradas, adicionadas con vitaminas y hierro. Para snackear.",
    "price": 1,
    "categoryId": "cereal",
    "image": "products_0026_20231206_132500.png"
  },
  {
    "id": "p26",
    "name": "Kellogg's Froot Loops",
    "short": "Cereal de maíz, trigo y avena",
    "description": "Aros de cereal con sabores naturales a frutas, adicionado con vitaminas y minerales.",
    "price": 1,
    "categoryId": "cereal",
    "image": "products_0027_20231206_132510.png"
  },
  {
    "id": "p27",
    "name": "Kellogg's Zucaritas Chocolate",
    "short": "Hojuelas de maíz sabor chocolate",
    "description": "Hojuelas de maíz escarchadas con sabor a chocolate y con malvaviscos, adicionadas con vitaminas y hierro.",
    "price": 1.1,
    "categoryId": "cereal",
    "image": "products_0028_20231206_132525.png"
  },
  {
    "id": "p28",
    "name": "Kellogg's Corn Pops",
    "short": "Maíz inflado y endulzado",
    "description": "Cereal de maíz inflado y endulzado, perfecto para el snack. Adicionado con vitaminas y hierro.",
    "price": 1,
    "categoryId": "cereal",
    "image": "products_0029_20231206_132532.png"
  },
  {
    "id": "p29",
    "name": "Nestlé Coffee-Mate",
    "short": "Sustituto de crema para café",
    "description": "Sustituto de crema en polvo no lácteo, para un café rico y cremoso. Venta individual.",
    "price": 0.2,
    "categoryId": "pantry",
    "image": "products_0030_20231206_132539.png"
  },
  {
    "id": "p30",
    "name": "Ricolino Panditas Clásicos",
    "short": "Gomitas de sabores frutales",
    "description": "Clásicas gomitas en forma de oso con deliciosos sabores frutales.",
    "price": 0.5,
    "categoryId": "candy",
    "image": "products_0031_20231206_132551.png"
  },
  {
    "id": "p31",
    "name": "Gamesa Mini Mamut",
    "short": "Galletas con malvavisco",
    "description": "Pequeñas galletas con malvavisco y cobertura sabor a chocolate. Un clásico para disfrutar.",
    "price": 0.4,
    "categoryId": "snacks",
    "image": "products_0032_20231206_132602.png"
  },
  {
    "id": "p32",
    "name": "The King Capsule",
    "short": "Cigarrillos con cápsula de sabor",
    "description": "Caja de cigarrillos The King con cápsula de sabor para una experiencia refrescante.",
    "price": 6,
    "categoryId": "tobacco",
    "image": "products_0033_20231206_132631.png"
  },
  {
    "id": "p33",
    "name": "Kitt Maní Barbacoa",
    "short": "Maní con sabor a barbacoa",
    "description": "Delicioso maní tostado con un intenso sabor a barbacoa. El snack perfecto.",
    "price": 0.9,
    "categoryId": "snacks",
    "image": "products_0034_20231206_132642.png"
  },
  {
    "id": "p34",
    "name": "Cremica Cremelo Orange",
    "short": "Galletas de crema sabor naranja",
    "description": "Galletas tipo wafer con un delicioso relleno cremoso sabor a naranja.",
    "price": 0.7,
    "categoryId": "snacks",
    "image": "products_0035_20231206_132718.png"
  },
  {
    "id": "p35",
    "name": "Cremica Cremelo Strawberry",
    "short": "Galletas de crema sabor fresa",
    "description": "Galletas tipo wafer con un delicioso relleno cremoso sabor a fresa.",
    "price": 0.7,
    "categoryId": "snacks",
    "image": "products_0036_20231206_132722.png"
  },
  {
    "id": "p36",
    "name": "Cremica Cremelo Vanilla",
    "short": "Galletas de crema sabor vainilla",
    "description": "Galletas tipo wafer con un delicioso relleno cremoso sabor a vainilla.",
    "price": 0.7,
    "categoryId": "snacks",
    "image": "products_0037_20231206_132728.png"
  },
  {
    "id": "p37",
    "name": "Cremica Cremelo Chocolate",
    "short": "Galletas de crema sabor chocolate",
    "description": "Galletas tipo wafer con un delicioso relleno cremoso sabor a chocolate.",
    "price": 0.7,
    "categoryId": "snacks",
    "image": "products_0038_20231206_132733.png"
  },
  {
    "id": "p38",
    "name": "Kirkland Signature Palomitas",
    "short": "Palomitas de maíz sabor mantequilla",
    "description": "Palomitas para microondas con saborizante natural a mantequilla. Hechas con grano entero de maíz y sin gluten.",
    "price": 1.2,
    "categoryId": "snacks",
    "image": "products_0039_20231206_132759.png"
  },
  {
    "id": "p39",
    "name": "Member's Mark Malvaviscos",
    "short": "Malvaviscos sabor fresa y vainilla",
    "description": "Bolsa de 1kg de suaves malvaviscos con sabores de fresa y vainilla.",
    "price": 4.5,
    "categoryId": "candy",
    "image": "products_0040_20231206_133000.png"
  },
  {
    "id": "p40",
    "name": "Knorr Caldo de Pollo en Polvo",
    "short": "Caldo de pollo en polvo 1kg",
    "description": "Caldo de pollo en polvo para sazonar tus comidas. Bolsa resellable de 1kg, fácil disolución.",
    "price": 8,
    "categoryId": "pantry",
    "image": "products_0041_20231206_133230.png"
  },
  {
    "id": "p41",
    "name": "Knorr Caldo de Pollo en Cubos",
    "short": "24 cubos de caldo de pollo",
    "description": "Caldo de pollo en cubos para un irresistible sabor casero. Caja con 24 cubos.",
    "price": 3,
    "categoryId": "pantry",
    "image": "products_0042_20231206_133237.png"
  },
  {
    "id": "p42",
    "name": "Kellogg's Choco Krispis",
    "short": "Arroz inflado sabor a chocolate",
    "description": "Cereal de granos de arroz inflados con el clásico sabor a chocolate, adicionados con vitaminas y minerales.",
    "price": 1.1,
    "categoryId": "cereal",
    "image": "products_0043_20231206_133243.png"
  },
  {
    "id": "p43",
    "name": "Zuko Sabor Naranja",
    "short": "Polvo para preparar bebida",
    "description": "Polvo para preparar 2 litros de bebida sabor naranja. Adicionado con vitamina C, no requiere azúcar.",
    "price": 0.5,
    "categoryId": "beverages",
    "image": "products_0044_20231206_133251.png"
  },
  {
    "id": "p44",
    "name": "Zuko Sabor Manzana",
    "short": "Polvo para preparar bebida",
    "description": "Polvo para preparar 2 litros de bebida sabor manzana. Adicionado con vitamina C, no requiere azúcar.",
    "price": 0.5,
    "categoryId": "beverages",
    "image": "products_0045_20231206_133257.png"
  },
  {
    "id": "p45",
    "name": "Zuko Sabor Limón",
    "short": "Polvo para preparar bebida",
    "description": "Polvo para preparar 2 litros de bebida sabor limón. Adicionado con vitamina C, no requiere azúcar.",
    "price": 0.5,
    "categoryId": "beverages",
    "image": "products_0046_20231206_133302.png"
  },
  {
    "id": "p46",
    "name": "RikoPollo Caldito de Pollo",
    "short": "Sazonador sabor a caldito de pollo",
    "description": "Sazonador con delicioso sabor a caldito de pollo para realzar el sabor de tus comidas.",
    "price": 0.6,
    "categoryId": "pantry",
    "image": "products_0047_20231206_133319.png"
  },
  {
    "id": "p47",
    "name": "Maizena Fécula de Maíz",
    "short": "Fécula de maíz",
    "description": "La original fécula de maíz Maizena. Ideal para hacer tus platillos más crujientes, cremosos y esponjosos.",
    "price": 1,
    "categoryId": "pantry",
    "image": "products_0048_Capa-1.png"
  },
  {
    "id": "p48",
    "name": "DoBon Composto Lácteo",
    "short": "Compuesto lácteo en polvo",
    "description": "Compuesto lácteo en polvo de 1kg. Fuente de Calcio, Hierro y Vitaminas A, C y D.",
    "price": 7.5,
    "categoryId": "dairy",
    "image": "products_0049_Capa-2.png"
  },
  {
    "id": "p49",
    "name": "WS Blended Spirit Drink",
    "short": "Bebida espirituosa mezclada",
    "description": "Bebida espirituosa mezclada, 'Rare Luxury', una selección de calidad para disfrutar.",
    "price": 15,
    "categoryId": "beverages",
    "image": "products_0050_IMG_20231206_123431.png"
  },
  {
    "id": "p50",
    "name": "Cerveza 86 Original",
    "short": "Cerveza premium panameña",
    "description": "Cerveza 86 Original, una cerveza premium panameña con un sabor único y refrescante. Perfecta para cualquier ocasión.",
    "price": 2.5,
    "categoryId": "beverages",
    "image": "86 Original.png"
  },
  {
    "id": "p51",
    "name": "Cerveza Claro",
    "short": "Cerveza clara premium",
    "description": "Cerveza Claro, una cerveza clara premium con un sabor suave y equilibrado. Ideal para disfrutar en compañía.",
    "price": 2.2,
    "categoryId": "beverages",
    "image": "Claro.png"
  },
  {
    "id": "p52",
    "name": "Cerveza Hollandia",
    "short": "Cerveza holandesa premium",
    "description": "Cerveza Hollandia, una cerveza premium de origen holandés con un sabor distintivo y de alta calidad.",
    "price": 2.8,
    "categoryId": "beverages",
    "image": "Hollandia.png"
  },
  {
    "id": "p53",
    "name": "Cerveza Lander Brau",
    "short": "Cerveza artesanal panameña",
    "description": "Cerveza Lander Brau, una cerveza artesanal panameña con carácter único y sabor excepcional.",
    "price": 3.0,
    "categoryId": "beverages",
    "image": "Lander Brau.png"
  },
  {
    "id": "p54",
    "name": "Cerveza Windmill",
    "short": "Cerveza premium holandesa",
    "description": "Cerveza Windmill, una cerveza premium holandesa con un sabor suave y refrescante. Tradición cervecera en cada sorbo.",
    "price": 2.7,
    "categoryId": "beverages",
    "image": "Windmill.png"
  },
  {
    "id": "p55",
    "name": "Cerveza Bavaria",
    "short": "Cerveza holandesa clásica",
    "description": "Cerveza Bavaria, una cerveza holandesa clásica con más de 300 años de tradición cervecera. Sabor inconfundible.",
    "price": 2.9,
    "categoryId": "beverages",
    "image": "Bavaria.png"
  }
]